monocle_test_tools/__init__.py
monocle_test_tools/constants.py
monocle_test_tools/fluent_api.py
monocle_test_tools/gitutils.py
monocle_test_tools/pytest_plugin.py
monocle_test_tools/schema.py
monocle_test_tools/trace_utils.py
monocle_test_tools/validator.py
monocle_test_tools/comparer/__init__.py
monocle_test_tools/comparer/base_comparer.py
monocle_test_tools/comparer/bert_score_comparer.py
monocle_test_tools/comparer/comparer_manager.py
monocle_test_tools/comparer/default_comparer.py
monocle_test_tools/comparer/metric_comparer.py
monocle_test_tools/comparer/sentense_comparer.py
monocle_test_tools/comparer/token_match_comparer.py
monocle_test_tools/evals/__init__.py
monocle_test_tools/evals/base_eval.py
monocle_test_tools/evals/bert_eval.py
monocle_test_tools/evals/eval_manager.py
monocle_test_tools/runner/__init__.py
monocle_test_tools/runner/adk_runner.py
monocle_test_tools/runner/agent_runner.py
monocle_test_tools/runner/crewai_runner.py
monocle_test_tools/runner/lg_runner.py
monocle_test_tools/runner/llamaindex_runner.py
monocle_test_tools/runner/openai_runner.py
monocle_test_tools/runner/runner.py
monocle_test_tools-0.7.2.dist-info/METADATA
monocle_test_tools-0.7.2.dist-info/WHEEL
monocle_test_tools-0.7.2.dist-info/entry_points.txt
monocle_test_tools-0.7.2.dist-info/licenses/LICENSE
monocle_test_tools-0.7.2.dist-info/RECORD
