Metadata-Version: 2.4
Name: monocle_test_tools
Version: 0.7.2
Summary: Testing and validation framework for monocle AI agent tracing
Project-URL: Homepage, https://github.com/monocle2ai/monocle
Project-URL: Issues, https://github.com/monocle2ai/monocle/issues
Project-URL: Repository, https://github.com/monocle2ai/monocle
Project-URL: Documentation, http://monocle2ai.org
Author-email: "Okahu Inc." <okahu-pypi@okahu.ai>
License: Apache-2.0
License-File: LICENSE
Classifier: Development Status :: 3 - Alpha
Classifier: Intended Audience :: Developers
Classifier: License :: OSI Approved :: Apache Software License
Classifier: Operating System :: OS Independent
Classifier: Programming Language :: Python :: 3
Classifier: Topic :: Scientific/Engineering :: Artificial Intelligence
Classifier: Topic :: Software Development :: Testing
Requires-Python: >=3.8
Requires-Dist: bert-score>=0.3.0
Requires-Dist: gitpython==3.1.45
Requires-Dist: jsonschema>=4.0.0
Requires-Dist: monocle-apptrace>=0.5.0
Requires-Dist: pydantic>=2.11.7
Requires-Dist: pytest-asyncio>=0.26.0
Requires-Dist: pytest>=8.0.0
Requires-Dist: sentence-transformers==3.3.0
Requires-Dist: transformers>=4.0.0
Provides-Extra: all
Requires-Dist: black>=23.0.0; extra == 'all'
Requires-Dist: crewai==0.95.0; extra == 'all'
Requires-Dist: flake8>=6.0.0; extra == 'all'
Requires-Dist: google-adk==1.10.0; extra == 'all'
Requires-Dist: google-generativeai==0.8.5; extra == 'all'
Requires-Dist: langchain-openai; extra == 'all'
Requires-Dist: mypy>=1.0.0; extra == 'all'
Requires-Dist: openai-agents==0.2.6; extra == 'all'
Requires-Dist: pre-commit>=3.0.0; extra == 'all'
Requires-Dist: pytest-cov>=4.0.0; extra == 'all'
Provides-Extra: dev
Requires-Dist: black>=23.0.0; extra == 'dev'
Requires-Dist: crewai==0.95.0; extra == 'dev'
Requires-Dist: flake8>=6.0.0; extra == 'dev'
Requires-Dist: google-adk==1.10.0; extra == 'dev'
Requires-Dist: google-generativeai==0.8.5; extra == 'dev'
Requires-Dist: langchain-openai; extra == 'dev'
Requires-Dist: mypy>=1.0.0; extra == 'dev'
Requires-Dist: openai-agents==0.2.6; extra == 'dev'
Requires-Dist: pre-commit>=3.0.0; extra == 'dev'
Requires-Dist: pytest-cov>=4.0.0; extra == 'dev'
